xhook/__init__.py
xhook/__main__.py
xhook-0.0.1.dist-info/LICENSE
xhook-0.0.1.dist-info/METADATA
xhook-0.0.1.dist-info/WHEEL
xhook-0.0.1.dist-info/RECORD
