Metadata-Version: 2.1
Name: xhook
Version: 0.0.1
Summary: xhook client library for python
License: LICENSE
Author: Marc Ford
Author-email: marc@massive.sh
Requires-Python: >=3.10,<4.0
Classifier: License :: Other/Proprietary License
Classifier: Programming Language :: Python :: 3
Classifier: Programming Language :: Python :: 3.10
Classifier: Programming Language :: Python :: 3.11
Classifier: Programming Language :: Python :: 3.12
Requires-Dist: aiohttp (>=3.10.10,<4.0.0)
